MANIFEST.in
crm_lead_view.xml
crm_partner_assign_data.xml
res_partner_demo.xml
res_partner_view.xml
setup.py
./__init__.py
./__openerp__.py
./crm_partner_assign.py
./report/__init__.py
./report/crm_lead_report.py
./report/crm_partner_report.py
./wizard/__init__.py
./wizard/crm_forward_to_partner.py
i18n/ar.po
i18n/bg.po
i18n/bs.po
i18n/ca.po
i18n/crm_partner_assign.pot
i18n/cs.po
i18n/da.po
i18n/de.po
i18n/el.po
i18n/es.po
i18n/es_CR.po
i18n/es_MX.po
i18n/es_PY.po
i18n/es_VE.po
i18n/fi.po
i18n/fr.po
i18n/gl.po
i18n/hr.po
i18n/hu.po
i18n/it.po
i18n/ja.po
i18n/ko.po
i18n/lt.po
i18n/lv.po
i18n/mk.po
i18n/mn.po
i18n/nb.po
i18n/nl.po
i18n/pl.po
i18n/pt.po
i18n/pt_BR.po
i18n/ro.po
i18n/ru.po
i18n/sl.po
i18n/sq.po
i18n/sr@latin.po
i18n/sv.po
i18n/tr.po
i18n/zh_CN.po
i18n/zh_TW.po
images/partner_geo_localization.jpeg
images/partner_grade.jpeg
openerp_crm_partner_assign.egg-info/PKG-INFO
openerp_crm_partner_assign.egg-info/SOURCES.txt
openerp_crm_partner_assign.egg-info/dependency_links.txt
openerp_crm_partner_assign.egg-info/requires.txt
openerp_crm_partner_assign.egg-info/top_level.txt
report/crm_lead_report_view.xml
report/crm_partner_report_view.xml
security/ir.model.access.csv
test/partner_assign.yml
wizard/crm_forward_to_partner_view.xml